README.rst
setup.py
lever/__init__.py
lever/acl.py
lever/base.py
lever/mapper.py
lever.egg-info/PKG-INFO
lever.egg-info/SOURCES.txt
lever.egg-info/dependency_links.txt
lever.egg-info/requires.txt
lever.egg-info/top_level.txt
lever/tests/__init__.py
lever/tests/acl_tests.py
lever/tests/model_helpers.py
lever/tests/unit_tests.py