Metadata-Version: 1.0
Name: lever
Version: 0.2.4
Summary: A tool for exposing SQLAlchemy models in Flask via REST
Home-page: http://www.python.org/sigs/distutils-sig/
Author: Isaac Cook
Author-email: isaac@crowdlink.io
License: UNKNOWN
Platform: UNKNOWN
